taggit_selectize/__init__.py
taggit_selectize/conf.py
taggit_selectize/managers.py
taggit_selectize/urls.py
taggit_selectize/utils.py
taggit_selectize/views.py
taggit_selectize/widgets.py
taggit_selectize/static/taggit_selectize/css/selectize.django.css
taggit_selectize/static/taggit_selectize/js/selectize.js
taggit_selectize-2.10.0.dist-info/AUTHORS.rst
taggit_selectize-2.10.0.dist-info/LICENSE
taggit_selectize-2.10.0.dist-info/METADATA
taggit_selectize-2.10.0.dist-info/WHEEL
taggit_selectize-2.10.0.dist-info/top_level.txt
taggit_selectize-2.10.0.dist-info/RECORD
