Metadata-Version: 2.1
Name: taggit-selectize
Version: 2.10.0
Summary: django-taggit + selectize.js
Home-page: https://github.com/chhantyal/taggit-selectize
Author: Nar Chhantyal
Author-email: nkchhantyal@gmail.com
License: BSD
Keywords: taggit-selectize
Platform: UNKNOWN
Classifier: Development Status :: 2 - Pre-Alpha
Classifier: Framework :: Django
Classifier: Intended Audience :: Developers
Classifier: License :: OSI Approved :: BSD License
Classifier: Natural Language :: English
Classifier: Programming Language :: Python :: 2
Classifier: Programming Language :: Python :: 3
